{
    "name": "Clothing Designer",
    "truename": 1,
    "artists": "?",
    "sources": "CPI SoundCloud",
    "sourcelinks": "https://soundcloud.com/user-764833925/clothing-designer",
    "versions": [
        {
            "info": "",
            "name": "Clothing Designer [440725173].mp3",
            "source": "CPI SoundCloud"
        }
    ],
    "cpi": {
        "files": [
            {
                "info": "",
                "name": "?"
            }
        ],
        "uses": "Clothing Customizer",
        "date": "2018/12/20",
        "truedate": 0
    }
}