{
    "cp": {
        "Earliest Date": "?",
        "Order": 190.5,
        "Related To": "Operation: Hot Sauce",
        "uses": [
            {
                "date": "?",
                "files": "",
                "info": "",
                "use": "Operation: Hot Sauce"
            }
        ]
    },
    "Composers": "?",
    "Earliest Date": "?",
    "HQ Source(s)": "SWF Director Closeup",
    "Link": "",
    "Medias": "Club Penguin",
    "Name": "Director Jingle",
    "Name_official": 0,
    "Order": 190.5
}