{
    "name": "Event Prep",
    "truename": 1,
    "artists": "Curt Macdonald",
    "altnames": "",
    "sources": "Other",
    "sourcelinks": "https://web.archive.org/web/20210928075227oe_/https://s3.amazonaws.com/preview.freshmusic.com/2123/2123_06.m4a",
    "order": 18,
    "link": "https://youtu.be/clyysAx8yGc",
    "cp": {
        "order": 18,
        "uses": [
            {
                "date": "2006/08/11",
                "files": "",
                "info": "",
                "use": "Sports Party"
            },
            {
                "date": "?",
                "files": "",
                "info": "",
                "use": "Penguin Games"
            },
            {
                "date": "?",
                "files": "",
                "info": "",
                "use": "Puffle Party 2011"
            },
            {
                "date": "?",
                "files": "",
                "info": "",
                "use": "Puffle party 2012"
            }
        ]
    },
    "app": {
        "order": 1,
        "uses": [
            {
                "date": "?",
                "files": "",
                "info": "",
                "use": "Igloo"
            },
            {
                "date": "?",
                "files": "",
                "info": "",
                "use": "Fashion Party"
            }
        ]
    }
}