{
    "Alternate Names": "",
    "app": {
        "Earliest Date": "?",
        "Order": 1,
        "Related To": "Igloo",
        "uses": [
            {
                "date": "?",
                "files": "",
                "info": "",
                "use": "Igloo"
            }
        ]
    },
    "cp": {
        "Earliest Date": "2014/11/20",
        "Order": 294,
        "Related To": "Pirate Party, Inside Out Party",
        "uses": [
            {
                "date": "2014/11/20",
                "files": "",
                "info": "",
                "use": "Pirate Party"
            },
            {
                "date": "?",
                "files": "",
                "info": "",
                "use": "Inside Out Party"
            }
        ]
    },
    "Composers": "Norrie Henderson",
    "Earliest Date": "2014/11/20",
    "HQ Source(s)": "SoundCloud",
    "Link": "",
    "Medias": "Club Penguin",
    "Name": "Fair Winds",
    "Name_official": 1,
    "Order": 294
}