{
    "name": "Herbert Style",
    "truename": 1,
    "artists": "Norrie Henderson",
    "altnames": "",
    "sources": "App + Club Penguin Youtube Channel",
    "link": "",
    "cp": {
        "uses": "?, Cave Maze, Operation: Tri-umph",
        "date": "2012/11/23",
        "truedate": 1
    },
    "app": {
        "uses": "Igloo",
        "date": "2018/12/20",
        "truedate": 0
    },
    "versions": [
        {
            "name": "MUS_351_Igloo_HerbertStyle.mp3",
            "info": "",
            "source": "App"
        },
        {
            "name": "Herbert Style! - Official Music Video - Disney Club Penguin-ILf7BwPI6hU.wav",
            "info": "",
            "source": "Club Penguin Youtube Channel"
        }
    ]
}