{
    "Alternate Names": "",
    "App Info": {
        "Earliest Date": "?",
        "Order": 1,
        "Related To": "Igloo, Fashion Party"
    },
    "CP Flash Info": {
        "Earliest Date": "2015/02/19",
        "Order": 318,
        "Related To": "SoundStudio Party"
    },
    "Composers": "?",
    "Earliest Date": "2015/02/19",
    "HQ Source(s)": "App",
    "Link": "",
    "Medias": "Club Penguin",
    "Name": "Made of Stars",
    "Name_official": 1,
    "Order": 318
}