{
    "name": "Olaf's Greeting",
    "truename": 1,
    "artists": "?",
    "altnames": "",
    "sources": "App",
    "link": "",
    "cp": {
        "uses": "Frozen Fever Party",
        "date": "2016/08/17/2",
        "truedate": 1
    },
    "app": {
        "uses": "Igloo, Frozen Party",
        "date": "2018/12/20",
        "truedate": 0
    },
    "versions": [
        {
            "name": "MUS_962_Igloo_OlafsGreeting.mp3",
            "info": "",
            "source": "App"
        }
    ]
}