{
    "Alternate Names": "Puffle Hotel Rooftop",
    "App Info": {
        "Earliest Date": "?",
        "Order": 1,
        "Related To": "Rooftop Pool"
    },
    "CP Flash Info": {
        "Earliest Date": "2013/03/21",
        "Order": 188,
        "Related To": "Rooftop Pool"
    },
    "CPI Info": {
        "Earliest Date": "?",
        "Order": 1,
        "Related To": "Town"
    },
    "Composers": "Norrie Henderson",
    "Earliest Date": "2013/03/21",
    "HQ Source(s)": "App + CPI SoundCloud",
    "Link": "",
    "Medias": "Club Penguin",
    "Name": "Puffle Dance Rock Mix",
    "Name_official": 1,
    "Order": 188
}