{
    "Alternate Names": "",
    "App Info": {
        "Earliest Date": "?",
        "Order": 1,
        "Related To": "Igloo, Holiday Party 2014"
    },
    "CP Flash Info": {
        "Earliest Date": "2014/12/18",
        "Order": 301,
        "Related To": "Merry Walrus Party"
    },
    "Composers": "?",
    "Earliest Date": "2014/12/18",
    "HQ Source(s)": "SoundCloud",
    "Link": "",
    "Medias": "Club Penguin",
    "Name": "Ring In the Cheer",
    "Name_official": 1,
    "Order": 301
}