{
    "Alternate Names": "Rock Rink, Let The Game Begin, Rock N Roll",
    "CP Flash Info": {
        "Earliest Date": "2008/07/25",
        "Order": 71,
        "Related To": "Music Jam, Penguin Games, Penguin Cup"
    },
    "Composers": "Friction Music",
    "Earliest Date": "2008/07/25",
    "Game Day Info": {
        "Earliest Date": "2010/09/17",
        "Order": 8,
        "Related To": "Goal!"
    },
    "HQ Source(s)": "SoundCloud + Game Day",
    "Link": "https://www.youtube.com/watch?v=r9eUD9N9gAk",
    "Medias": "Club Penguin, Club Penguin: Game Day!",
    "Name": "Rock Rink",
    "Name_official": 1,
    "Order": 71,
    "versions": {
        "1": {
            "info": "Highest quality version, but incomplete, missing the ending.",
            "name": "ig_IH_00.brstm",
            "source": "Game Day"
        },
        "2": {
            "info": "Highest quality version that is complete.",
            "name": "MUS_271_Igloo_AmbientRiffing.mp3",
            "source": "App"
        }
    }
}