{
    "name": "Sunshine Cruisin'",
    "truename": 1,
    "artists": "?",
    "altnames": "",
    "sources": "App",
    "order": 381,
    "link": "",
    "cp": {
        "order": 381,
        "uses": [
            {
                "date": "2017/01/04",
                "use": "Club Penguin Island Party",
                "files": "",
                "info": ""
            }
        ]
    },
    "app": {
        "order": 1,
        "uses": [
            {
                "date": "?",
                "use": "Igloo",
                "files": "",
                "info": ""
            }
        ]
    }
}