{
    "Alternate Names": "Ye Knight's Quest Theme",
    "App Info": {
        "Earliest Date": "?",
        "Order": 1,
        "Related To": "Igloo"
    },
    "CP Flash Info": {
        "Earliest Date": "2009/05/08",
        "Order": 100,
        "Related To": "Medieval Party"
    },
    "Composers": "Chris Hendricks",
    "Earliest Date": "2009/05/08",
    "HQ Source(s)": "App",
    "Link": "https://www.youtube.com/watch?v=rlw8HofVLJo",
    "Medias": "Club Penguin",
    "Name": "The Quest",
    "Name_official": 1,
    "Order": 100
}