{
    "name": "Pirates And Monkeys",
    "truename": 1,
    "artists": "Chris Hendricks",
    "altnames": "Island Adventure 2010 Main Theme",
    "sources": "Youtube",
    "sourcelinks": "https://youtu.be/e1ufA7zt5BU",
    "order": 135,
    "link": "https://youtu.be/eCN-H4Cfnyg",
    "cp": {
        "order": 135,
        "uses": [
            {
                "date": "2010/06/17",
                "end": "2010/06/27",
                "use": "Island Adventure Party 2010",
                "files": "",
                "info": ""
            },
            {
                "date": "2011/07/21",
                "end": "2011/08/04",
                "use": "Island Adventure Party 2011",
                "files": "",
                "info": ""
            },
            {
                "date": "2012/03/15",
                "end": "2012/03/29",
                "use": "Puffle Party 2012",
                "files": "",
                "info": ""
            },
            {
                "date": "2013/03/21",
                "end": "2013/04/05",
                "use": "Puffle Party 2013",
                "files": "",
                "info": ""
            },
            {
                "date": "2013/08/22",
                "end": "2013/09/04",
                "use": "Teen Beach Movie Summer Jam",
                "files": "",
                "info": ""
            },
            {
                "date": "2014/04/17",
                "end": "2014/05/01",
                "use": "Puffle Party 2014",
                "files": "",
                "info": ""
            },
            {
                "date": "?",
                "use": "Anniversary Party (??)",
                "files": "",
                "info": ""
            }
        ]
    },
    "app": {
        "order": 1,
        "uses": [
            {
                "date": "?",
                "use": "Igloo",
                "files": "",
                "info": ""
            }
        ]
    }
}