{
    "name": "CP Music Mashup 2015",
    "truename": 1,
    "artists": "?",
    "altnames": "",
    "sources": "App + Club Penguin Youtube Channel",
    "order": 377,
    "link": "",
    "cp": {
        "order": 377,
        "uses": [
            {
                "date": "2016/01/07",
                "files": "",
                "info": "",
                "use": "?"
            },
            {
                "date": "?",
                "files": "",
                "info": "",
                "use": "Igloo"
            }
        ]
    },
    "app": {
        "order": 1,
        "uses": [
            {
                "date": "?",
                "files": "",
                "info": "",
                "use": "Igloo"
            }
        ]
    }
}